dblp/__init__.py
dblp-0.1.0.dist-info/DESCRIPTION.rst
dblp-0.1.0.dist-info/METADATA
dblp-0.1.0.dist-info/RECORD
dblp-0.1.0.dist-info/WHEEL
dblp-0.1.0.dist-info/metadata.json
dblp-0.1.0.dist-info/top_level.txt
