Metadata-Version: 2.0
Name: dblp
Version: 0.1.0
Summary: Downloads and formats search results from dblp
Home-page: https://github.com/sebastianGehrmann/dblp-pub/tree/master
Author: Sebastian Gehrmann
Author-email: gehrmann@seas.harvard.edu
License: LICENSE.txt
Platform: UNKNOWN
Requires-Dist: beautifulsoup4 (>=4.3.2)
Requires-Dist: pandas (>=0.16.2)
Requires-Dist: requests (>=2.7.0)
